locate_me/__init__.py
locate_me/helpers.py
locate_me/maps.py
locate_me-0.0.7a.dist-info/DESCRIPTION.rst
locate_me-0.0.7a.dist-info/METADATA
locate_me-0.0.7a.dist-info/RECORD
locate_me-0.0.7a.dist-info/WHEEL
locate_me-0.0.7a.dist-info/entry_points.txt
locate_me-0.0.7a.dist-info/metadata.json
locate_me-0.0.7a.dist-info/top_level.txt
